effiara/__init__.py
effiara/agreement.py
effiara/annotator_reliability.py
effiara/data_generator.py
effiara/preparation.py
effiara/utils.py
effiara/label_generators/__init__.py
effiara/label_generators/effi_label_generator.py
effiara/label_generators/label_generator.py
effiara/label_generators/ordinal_label_generator.py
effiara/label_generators/topic_label_generator.py
effiara-0.1.1.dist-info/METADATA
effiara-0.1.1.dist-info/WHEEL
effiara-0.1.1.dist-info/top_level.txt
effiara-0.1.1.dist-info/RECORD
